crabpy_pyramid/__init__.py
crabpy_pyramid/adressenregister.py
crabpy_pyramid/capakey.py
crabpy_pyramid/utils.py
crabpy_pyramid/renderers/__init__.py
crabpy_pyramid/renderers/adressenregister.py
crabpy_pyramid/renderers/capakey.py
crabpy_pyramid/routes/__init__.py
crabpy_pyramid/routes/adressenregister.py
crabpy_pyramid/routes/capakey.py
crabpy_pyramid/views/__init__.py
crabpy_pyramid/views/adressenregister.py
crabpy_pyramid/views/capakey.py
crabpy_pyramid/views/exceptions.py
crabpy_pyramid/views/utils.py
crabpy_pyramid-2.2.0.dist-info/METADATA
crabpy_pyramid-2.2.0.dist-info/WHEEL
crabpy_pyramid-2.2.0.dist-info/entry_points.txt
crabpy_pyramid-2.2.0.dist-info/licenses/LICENSE
crabpy_pyramid-2.2.0.dist-info/RECORD
