Metadata-Version: 2.1
Name: crabpy_pyramid
Version: 2.2.0
Summary: Bindings for the CRABpy webservices and the Pyramid framework.
Project-URL: Repository, https://github.com/OnroerendErfgoed/crabpy_pyramid.git
Project-URL: Issues, https://github.com/OnroerendErfgoed/crabpy_pyramid/issues
Project-URL: Changelog, https://github.com/OnroerendErfgoed/crabpy_pyramid/blob/master/CHANGES.rst
Author-email: Flanders Heritage Agency <ict@onroerenderfgoed.be>
License: The MIT License (MIT)
License-File: LICENSE
Keywords: AGIV,CAPAKEY,CRAB,pyramid,web,wsgi
Classifier: Development Status :: 5 - Production/Stable
Classifier: Framework :: Pyramid
Classifier: Intended Audience :: Developers
Classifier: License :: OSI Approved :: MIT License
Classifier: Operating System :: OS Independent
Classifier: Programming Language :: Python
Classifier: Programming Language :: Python :: 3.10
Classifier: Topic :: Internet :: WWW/HTTP
Requires-Python: <3.13,>=3.10
Requires-Dist: crabpy>=1.5.0
Requires-Dist: pycountry>=23.12.11
Requires-Dist: pyramid>=2.0.0
Provides-Extra: dev
Requires-Dist: black==24.10.0; extra == 'dev'
Requires-Dist: coveralls==4.0.1; extra == 'dev'
Requires-Dist: flake8-bugbear==24.8.19; extra == 'dev'
Requires-Dist: flake8-import-order==0.18.2; extra == 'dev'
Requires-Dist: flake8==7.1.1; extra == 'dev'
Requires-Dist: pytest==8.3.3; extra == 'dev'
Requires-Dist: responses==0.25.3; extra == 'dev'
Requires-Dist: uv==0.4.20; extra == 'dev'
Requires-Dist: waitress==3.0.0; extra == 'dev'
Requires-Dist: webtest==3.0.1; extra == 'dev'
